secure_env/__init__.py
secure_env/cli.py
secure_env/core.py
secure_env/exceptions.py
secure_env/utils.py
secure_env/examples/basic_usage.py
secure_env/examples/cli_usage.py
secure_env/tests/__init__.py
secure_env/tests/test_core.py
secure_env/tests/test_utils.py
secure_env-2.0.0.dist-info/licenses/LICENSE
secure_env-2.0.0.dist-info/METADATA
secure_env-2.0.0.dist-info/WHEEL
secure_env-2.0.0.dist-info/entry_points.txt
secure_env-2.0.0.dist-info/top_level.txt
secure_env-2.0.0.dist-info/RECORD
