Metadata-Version: 2.4
Name: secure-env
Version: 2.0.0
Summary: A simple and secure way to manage environment variables with AES encryption
Home-page: https://github.com/Moesthetics-code/secure-env
Author: Mohamed Ndiaye
Author-email: Mohamed Ndiaye <mintok2000@gmail.com>
Maintainer-email: Mohamed Ndiaye <mintok2000@gmail.com>
License-Expression: MIT
Project-URL: Homepage, https://github.com/Moesthetics-code/secure-env
Project-URL: Documentation, https://github.com/Moesthetics-code/secure-env#readme
Project-URL: Repository, https://github.com/Moesthetics-code/secure-env.git
Project-URL: Bug Reports, https://github.com/Moesthetics-code/secure-env/issues
Project-URL: Changelog, https://github.com/Moesthetics-code/secure-env/blob/main/CHANGELOG.md
Keywords: environment,variables,encryption,security,configuration,secrets
Classifier: Development Status :: 5 - Production/Stable
Classifier: Intended Audience :: Developers
Classifier: Topic :: Software Development :: Libraries :: Python Modules
Classifier: Topic :: Security :: Cryptography
Classifier: Topic :: System :: Systems Administration
Classifier: Programming Language :: Python :: 3
Classifier: Programming Language :: Python :: 3.7
Classifier: Programming Language :: Python :: 3.8
Classifier: Programming Language :: Python :: 3.9
Classifier: Programming Language :: Python :: 3.10
Classifier: Programming Language :: Python :: 3.11
Classifier: Programming Language :: Python :: 3.12
Classifier: Operating System :: OS Independent
Requires-Python: >=3.7
License-File: LICENSE
Requires-Dist: cryptography>=3.4.0
Provides-Extra: dev
Requires-Dist: pytest>=6.0; extra == "dev"
Requires-Dist: pytest-cov>=2.0; extra == "dev"
Requires-Dist: black>=21.0; extra == "dev"
Requires-Dist: flake8>=3.8; extra == "dev"
Requires-Dist: mypy>=0.910; extra == "dev"
Requires-Dist: twine>=3.0; extra == "dev"
Requires-Dist: wheel>=0.36; extra == "dev"
Requires-Dist: build>=0.7; extra == "dev"
Provides-Extra: test
Requires-Dist: pytest>=6.0; extra == "test"
Requires-Dist: pytest-cov>=2.0; extra == "test"
Dynamic: author
Dynamic: home-page
Dynamic: license-file
Dynamic: requires-python
